setup.py
tornado_stripe/__init__.py
tornado_stripe.egg-info/PKG-INFO
tornado_stripe.egg-info/SOURCES.txt
tornado_stripe.egg-info/dependency_links.txt
tornado_stripe.egg-info/requires.txt
tornado_stripe.egg-info/top_level.txt