Metadata-Version: 1.0
Name: tornado-stripe
Version: 1.0.3
Summary: Tornado client library for accessing Stripe API
Home-page: https://github.com/didip/tornado-stripe
Author: Didip Kerabat
Author-email: didipk@gmail.com
License: Apache Software License
Keywords: tornado stripe api
Platform: UNKNOWN
Classifier: License :: OSI Approved :: Apache Software License
Classifier: Programming Language :: Python :: 2.6
Classifier: Programming Language :: Python :: 2.7
Classifier: Development Status :: 4 - Beta
Classifier: Operating System :: OS Independent
